MANIFEST.in
README.txt
docs.pdf
docs.py
setup.py
strait.py
strait.egg-info/PKG-INFO
strait.egg-info/SOURCES.txt
strait.egg-info/dependency_links.txt
strait.egg-info/not-zip-safe
strait.egg-info/pbr.json
strait.egg-info/top_level.txt