Metadata-Version: 1.1
Name: strait
Version: 0.5.3
Summary: Simple Traits for Python
Home-page: http://pypi.python.org/pypi/strait
Author: Michele Simionato
Author-email: michele.simionato@gmail.com
License: BSD License
Platform: any
Classifier: Development Status :: 3 - Alpha
Classifier: Intended Audience :: Developers
Classifier: License :: OSI Approved :: BSD License
Classifier: Natural Language :: English
Classifier: Operating System :: OS Independent
Classifier: Programming Language :: Python
Classifier: Topic :: Software Development :: Libraries
